<?xml version="1.0" encoding="UTF-8" standalone="yes"?>
<c:chartSpace xmlns:c="http://schemas.openxmlformats.org/drawingml/2006/chart" xmlns:a="http://schemas.openxmlformats.org/drawingml/2006/main" xmlns:r="http://schemas.openxmlformats.org/officeDocument/2006/relationships"><c:date1904 val="0"/><c:lang val="en-US"/><c:roundedCorners val="0"/><mc:AlternateContent xmlns:mc="http://schemas.openxmlformats.org/markup-compatibility/2006"><mc:Choice Requires="c14" xmlns:c14="http://schemas.microsoft.com/office/drawing/2007/8/2/chart"><c14:style val="102"/></mc:Choice><mc:Fallback><c:style val="2"/></mc:Fallback></mc:AlternateContent><c:chart><c:autoTitleDeleted val="0"/><c:plotArea><c:layout/><c:scatterChart><c:scatterStyle val="smoothMarker"/><c:varyColors val="0"/><c:ser><c:idx val="0"/><c:order val="0"/><c:marker><c:symbol val="none"/></c:marker><c:yVal><c:numRef><c:f>Sheet1!$A$2:$A$36</c:f><c:numCache><c:formatCode>General</c:formatCode><c:ptCount val="35"/><c:pt idx="0"><c:v>0.3</c:v></c:pt><c:pt idx="1"><c:v>0.6</c:v></c:pt><c:pt idx="2"><c:v>0.6</c:v></c:pt><c:pt idx="3"><c:v>0.6</c:v></c:pt><c:pt idx="4"><c:v>0.3</c:v></c:pt><c:pt idx="5"><c:v>0.3</c:v></c:pt><c:pt idx="6"><c:v>0</c:v></c:pt><c:pt idx="7"><c:v>0</c:v></c:pt><c:pt idx="8"><c:v>0</c:v></c:pt><c:pt idx="9"><c:v>0</c:v></c:pt><c:pt idx="10"><c:v>0.3</c:v></c:pt><c:pt idx="11"><c:v>0.3</c:v></c:pt><c:pt idx="12"><c:v>0.3</c:v></c:pt><c:pt idx="13"><c:v>0.3</c:v></c:pt><c:pt idx="14"><c:v>0.3</c:v></c:pt><c:pt idx="15"><c:v>0.3</c:v></c:pt><c:pt idx="16"><c:v>0</c:v></c:pt><c:pt idx="17"><c:v>0</c:v></c:pt><c:pt idx="18"><c:v>0</c:v></c:pt><c:pt idx="19"><c:v>0</c:v></c:pt><c:pt idx="20"><c:v>0</c:v></c:pt><c:pt idx="21"><c:v>0</c:v></c:pt><c:pt idx="22"><c:v>0</c:v></c:pt><c:pt idx="23"><c:v>0</c:v></c:pt><c:pt idx="24"><c:v>0</c:v></c:pt><c:pt idx="25"><c:v>0</c:v></c:pt><c:pt idx="26"><c:v>0</c:v></c:pt><c:pt idx="27"><c:v>0</c:v></c:pt><c:pt idx="28"><c:v>0</c:v></c:pt><c:pt idx="29"><c:v>0</c:v></c:pt><c:pt idx="30"><c:v>0</c:v></c:pt><c:pt idx="31"><c:v>0</c:v></c:pt><c:pt idx="32"><c:v>0</c:v></c:pt><c:pt idx="33"><c:v>0</c:v></c:pt><c:pt idx="34"><c:v>0</c:v></c:pt></c:numCache></c:numRef></c:yVal><c:smooth val="1"/></c:ser><c:ser><c:idx val="1"/><c:order val="1"/><c:marker><c:symbol val="none"/></c:marker><c:yVal><c:numRef><c:f>Sheet1!$B$2:$B$36</c:f><c:numCache><c:formatCode>General</c:formatCode><c:ptCount val="35"/><c:pt idx="0"><c:v>-0.4</c:v></c:pt><c:pt idx="1"><c:v>-0.10000000000000003</c:v></c:pt><c:pt idx="2"><c:v>-0.10000000000000003</c:v></c:pt><c:pt idx="3"><c:v>-0.10000000000000003</c:v></c:pt><c:pt idx="4"><c:v>-0.10000000000000003</c:v></c:pt><c:pt idx="5"><c:v>-0.10000000000000003</c:v></c:pt><c:pt idx="6"><c:v>-0.10000000000000003</c:v></c:pt><c:pt idx="7"><c:v>-0.10000000000000003</c:v></c:pt><c:pt idx="8"><c:v>-0.10000000000000003</c:v></c:pt><c:pt idx="9"><c:v>-0.10000000000000003</c:v></c:pt><c:pt idx="10"><c:v>0.19999999999999996</c:v></c:pt><c:pt idx="11"><c:v>0.19999999999999996</c:v></c:pt><c:pt idx="12"><c:v>0.19999999999999996</c:v></c:pt><c:pt idx="13"><c:v>0.19999999999999996</c:v></c:pt><c:pt idx="14"><c:v>0.19999999999999996</c:v></c:pt><c:pt idx="15"><c:v>0.19999999999999996</c:v></c:pt><c:pt idx="16"><c:v>0.19999999999999996</c:v></c:pt><c:pt idx="17"><c:v>0.19999999999999996</c:v></c:pt><c:pt idx="18"><c:v>0.19999999999999996</c:v></c:pt><c:pt idx="19"><c:v>0.19999999999999996</c:v></c:pt><c:pt idx="20"><c:v>0.19999999999999996</c:v></c:pt><c:pt idx="21"><c:v>0.19999999999999996</c:v></c:pt><c:pt idx="22"><c:v>0.19999999999999996</c:v></c:pt><c:pt idx="23"><c:v>0.19999999999999996</c:v></c:pt><c:pt idx="24"><c:v>0.19999999999999996</c:v></c:pt><c:pt idx="25"><c:v>0.19999999999999996</c:v></c:pt><c:pt idx="26"><c:v>0.19999999999999996</c:v></c:pt><c:pt idx="27"><c:v>0.19999999999999996</c:v></c:pt><c:pt idx="28"><c:v>0.19999999999999996</c:v></c:pt><c:pt idx="29"><c:v>0.19999999999999996</c:v></c:pt><c:pt idx="30"><c:v>0.19999999999999996</c:v></c:pt><c:pt idx="31"><c:v>0.19999999999999996</c:v></c:pt><c:pt idx="32"><c:v>0.19999999999999996</c:v></c:pt><c:pt idx="33"><c:v>0.19999999999999996</c:v></c:pt><c:pt idx="34"><c:v>0.19999999999999996</c:v></c:pt></c:numCache></c:numRef></c:yVal><c:smooth val="1"/></c:ser><c:ser><c:idx val="2"/><c:order val="2"/><c:marker><c:symbol val="none"/></c:marker><c:yVal><c:numRef><c:f>Sheet1!$C$2:$C$36</c:f><c:numCache><c:formatCode>General</c:formatCode><c:ptCount val="35"/><c:pt idx="0"><c:v>0.8</c:v></c:pt><c:pt idx="1"><c:v>0.8</c:v></c:pt><c:pt idx="2"><c:v>0.8</c:v></c:pt><c:pt idx="3"><c:v>0.8</c:v></c:pt><c:pt idx="4"><c:v>0.8</c:v></c:pt><c:pt idx="5"><c:v>0.8</c:v></c:pt><c:pt idx="6"><c:v>0.8</c:v></c:pt><c:pt idx="7"><c:v>0.8</c:v></c:pt><c:pt idx="8"><c:v>0.8</c:v></c:pt><c:pt idx="9"><c:v>0.8</c:v></c:pt><c:pt idx="10"><c:v>0.8</c:v></c:pt><c:pt idx="11"><c:v>0.8</c:v></c:pt><c:pt idx="12"><c:v>0.8</c:v></c:pt><c:pt idx="13"><c:v>0.8</c:v></c:pt><c:pt idx="14"><c:v>0.8</c:v></c:pt><c:pt idx="15"><c:v>0.8</c:v></c:pt><c:pt idx="16"><c:v>0.8</c:v></c:pt><c:pt idx="17"><c:v>0.8</c:v></c:pt><c:pt idx="18"><c:v>0.8</c:v></c:pt><c:pt idx="19"><c:v>0.8</c:v></c:pt><c:pt idx="20"><c:v>0.8</c:v></c:pt><c:pt idx="21"><c:v>0.8</c:v></c:pt><c:pt idx="22"><c:v>0.8</c:v></c:pt><c:pt idx="23"><c:v>0.8</c:v></c:pt><c:pt idx="24"><c:v>0.8</c:v></c:pt><c:pt idx="25"><c:v>0.8</c:v></c:pt><c:pt idx="26"><c:v>0.8</c:v></c:pt><c:pt idx="27"><c:v>0.8</c:v></c:pt><c:pt idx="28"><c:v>0.8</c:v></c:pt><c:pt idx="29"><c:v>0.8</c:v></c:pt><c:pt idx="30"><c:v>0.8</c:v></c:pt><c:pt idx="31"><c:v>0.8</c:v></c:pt><c:pt idx="32"><c:v>0.8</c:v></c:pt><c:pt idx="33"><c:v>0.8</c:v></c:pt><c:pt idx="34"><c:v>0.8</c:v></c:pt></c:numCache></c:numRef></c:yVal><c:smooth val="1"/></c:ser><c:dLbls><c:showLegendKey val="0"/><c:showVal val="0"/><c:showCatName val="0"/><c:showSerName val="0"/><c:showPercent val="0"/><c:showBubbleSize val="0"/></c:dLbls><c:axId val="71521408"/><c:axId val="71522944"/></c:scatterChart><c:valAx><c:axId val="71521408"/><c:scaling><c:orientation val="minMax"/></c:scaling><c:delete val="0"/><c:axPos val="b"/><c:majorTickMark val="out"/><c:minorTickMark val="none"/><c:tickLblPos val="nextTo"/><c:crossAx val="71522944"/><c:crosses val="autoZero"/><c:crossBetween val="midCat"/></c:valAx><c:valAx><c:axId val="71522944"/><c:scaling><c:orientation val="minMax"/></c:scaling><c:delete val="0"/><c:axPos val="l"/><c:majorGridlines/><c:numFmt formatCode="General" sourceLinked="1"/><c:majorTickMark val="out"/><c:minorTickMark val="none"/><c:tickLblPos val="nextTo"/><c:crossAx val="71521408"/><c:crosses val="autoZero"/><c:crossBetween val="midCat"/></c:valAx></c:plotArea><c:legend><c:legendPos val="r"/><c:layout/><c:overlay val="0"/></c:legend><c:plotVisOnly val="1"/><c:dispBlanksAs val="gap"/><c:showDLblsOverMax val="0"/></c:chart><c:printSettings><c:headerFooter/><c:pageMargins b="0.75000000000000011" l="0.70000000000000007" r="0.70000000000000007" t="0.75000000000000011" header="0.30000000000000004" footer="0.30000000000000004"/><c:pageSetup/></c:printSettings></c:chartSpace>